{
    "link": "https://bbs.nga.cn/read.php?tid=40909621",
    "title": "调用断链兄弟萌都是怎么处理的？",
    "post_time": "2024-07-17 18:28",
    "uid": "61353120",
    "content": "今天看业务逻辑 上一个开发把消息落表之后调用就断了，去处理其他逻辑了。后续才知道是另有一个定时任务在抽表里的数据下发",
    "replies": [
        {
            "mid": "3260753",
            "mtime": "2024-07-17 19:29",
            "mcontent": "这不挺正常么 为啥一个调用要在一个服务里面从头走到尾啊 那要消息队列是干啥的"
        },
        {
            "mid": "63958521",
            "mtime": "2024-07-20 03:06",
            "mcontent": "你是在读代码还是在调试？读代码的话自己用脑子补，调试的话我也不知道。"
        },
        {
            "mid": "202131",
            "mtime": "2024-08-10 22:45",
            "mcontent": "从计划任务下发那里接起继续呗。落表后用定时任务发布也是计划的一部分。"
        },
        {
            "mid": "41657631",
            "mtime": "2024-08-11 00:47",
            "mcontent": "这有啥问题的吗？业务逻辑又不是总会在一块的"
        }
    ]
}