{
    "link": "https://bbs.nga.cn/read.php?tid=42239977",
    "title": "太难绷了，来吐槽一下自己",
    "post_time": "2024-10-28 08:37",
    "uid": "64813981",
    "content": "大一参加数模比赛，多目标规划模型写了个NSGA2来跑遗传。看他进化了一百次后看看进化效果，发现最聪明的小朋友一直是那一个，最笨的小朋友越来越笨了。",
    "replies": [
        {
            "mid": "65199167",
            "mtime": "2024-10-28 09:20",
            "mcontent": "进化就是优胜劣汰啊，虽然我学的生物不是IT相关的"
        },
        {
            "mid": "64813981",
            "mtime": "2024-10-28 09:45",
            "mcontent": "我意思是我写挂了，劣的越来越劣了"
        }
    ]
}