{
    "link": "https://bbs.nga.cn/read.php?tid=39052153",
    "title": "老板说要把目前服务器逻辑全都移到前端",
    "post_time": "2024-01-20 17:18",
    "uid": "9353863",
    "content": "因为想让玩家不联网也能玩",
    "replies": [
        {
            "mid": "60267071",
            "mtime": "2024-01-20 18:50",
            "mcontent": "游戏？"
        },
        {
            "mid": "60029705",
            "mtime": "2024-01-20 18:53",
            "mcontent": "啥内容啊"
        },
        {
            "mid": "60023955",
            "mtime": "2024-01-20 19:16",
            "mcontent": "利好破解单机版，不想赚钱了这是"
        },
        {
            "mid": "9353863",
            "mtime": "2024-01-20 19:37",
            "mcontent": "很多，主玩法，任务系统，还有其他乱七八糟的模块"
        },
        {
            "mid": "9353863",
            "mtime": "2024-01-20 19:38",
            "mcontent": "我想也是 还卖啥礼包啊 改改数据不是啥都有了"
        },
        {
            "mid": "63453772",
            "mtime": "2024-01-20 23:18",
            "mcontent": "全部前端你们是做端游？还是所谓手游单机版？"
        },
        {
            "mid": "43187732",
            "mtime": "2024-01-20 23:55",
            "mcontent": "那不就是单机游戏了吗。。。"
        },
        {
            "mid": "42252406",
            "mtime": "2024-01-21 03:21",
            "mcontent": "根据经验。。。1.服务器成本老板掏不起了。他的真实需求是减少服务器压力。2.大概架构类似 中继服务器。用户端本地计算，服务端负责数据下发与镜像验证。3.你可以琢磨一下这个架构对比现有架构的计算量差异以及额外增加的cdn花费。以及开发时间。如果非要你做，先试试任务部分的镜像验证吧。如果不要验证，那把最糟糕情况先说明，不要莫名奇妙背锅。毕竟老板外行是非常普遍的，过去野蛮发展吹上天了一群大字不认的猪。"
        }
    ]
}