{
    "link": "https://bbs.nga.cn/read.php?tid=41154969",
    "title": "[求助] 时间自由 如何用代码变现",
    "post_time": "2024-08-07 11:02",
    "uid": "63229597",
    "content": "曾在游戏公司工作过，因工作强度过高，辞职了，后回老家进了体制内，但是一直喜欢写代码鼓捣点东西，时间充裕该做点啥呢~",
    "replies": [
        {
            "mid": "63782286",
            "mtime": "2024-08-07 11:08",
            "mcontent": "这种帖子隔三差五就有一个"
        },
        {
            "mid": "26194130",
            "mtime": "2024-08-07 14:24",
            "mcontent": "接私活呗"
        },
        {
            "mid": "63229597",
            "mtime": "2024-08-08 08:40",
            "mcontent": "好吧~"
        },
        {
            "mid": "66005060",
            "mtime": "2024-08-08 16:22",
            "mcontent": "教我学代码也行"
        },
        {
            "mid": "62906736",
            "mtime": "2024-08-09 00:15",
            "mcontent": "搬运GitHub的代码到csdn，并配教程，就是行为比较脏"
        },
        {
            "mid": "65496206",
            "mtime": "2024-08-12 08:55",
            "mcontent": "太脏了，要关注这种我宁愿不看。"
        },
        {
            "mid": "65496206",
            "mtime": "2024-08-12 08:56",
            "mcontent": "怎么接私活，本职程序员也挺好奇。"
        },
        {
            "mid": "65496206",
            "mtime": "2024-08-12 08:57",
            "mcontent": "最近我在捣鼓QQ机器人，NAS，语言大模型本地部署，和SF画图本地部署。这种都蛮好玩的。在无聊可以自己写游戏，这个我也没坚持很久。"
        },
        {
            "mid": "62906736",
            "mtime": "2024-08-12 10:21",
            "mcontent": "做技术的是这样的，精神逼格高的一批，但有一天会为了生活低下高昂的头颅。我也这样"
        },
        {
            "mid": "65855073",
            "mtime": "2024-08-12 10:39",
            "mcontent": "流量大吗？基本上看到这些都直接关掉网页了"
        },
        {
            "mid": "62906736",
            "mtime": "2024-08-12 10:46",
            "mcontent": "如果写得细致，手把手教安装的，流量很大，无论是文章vip，还是下载资源付费，很多，而且c站又是国内最大的it轮胎"
        },
        {
            "mid": "65855073",
            "mtime": "2024-08-12 10:48",
            "mcontent": "啊这，没想到"
        },
        {
            "mid": "26194130",
            "mtime": "2024-08-12 14:44",
            "mcontent": ""
        },
        {
            "mid": "65345659",
            "mtime": "2024-08-12 15:45",
            "mcontent": "我也是，我是先考进来再辞职的"
        },
        {
            "mid": "65134325",
            "mtime": "2024-08-14 13:46",
            "mcontent": "马克一下"
        },
        {
            "mid": "61665887",
            "mtime": "2024-08-14 14:46",
            "mcontent": "去淘宝店问，人家接活，分发，你算是2包"
        },
        {
            "mid": "34940373",
            "mtime": "2024-08-14 23:58",
            "mcontent": "这个怎么变现"
        },
        {
            "mid": "62906736",
            "mtime": "2024-08-15 12:22",
            "mcontent": "就是我说的这样。"
        },
        {
            "mid": "61176345",
            "mtime": "2024-08-15 13:07",
            "mcontent": "有时间学两门外语，换工作身价高很多，何必私下没事找事，外包的价格狗看了都摇头"
        }
    ]
}