{
    "link": "https://bbs.nga.cn/read.php?tid=38671350",
    "title": "电脑网络有问题，有的网站能上，有的不能上。。",
    "post_time": "2023-12-12 16:48",
    "uid": "1332625",
    "content": "突然出现的这个问题，nga和好多其他网站连不上，但是百度，bili，新浪啥的都可以上，钢岚pc端也连不上，有大佬知道这是啥情况嘛",
    "replies": [
        {
            "mid": "62767347",
            "mtime": "2023-12-12 16:55",
            "mcontent": "如果是在公司摸鱼，那就是你们 it 部门做限制了如果是自己家里，可能是 dns 问题，改成自动匹配试试，不行就找运营商来解决"
        },
        {
            "mid": "1332625",
            "mtime": "2023-12-12 17:25",
            "mcontent": "同一个网的wifi，用手机就可以上，电脑就不行。。这样的话，是不是跟网络就没关系了"
        },
        {
            "mid": "60245480",
            "mtime": "2023-12-12 19:35",
            "mcontent": "改dns试试，常见的几个都试试，223.5.5.5，114.114.114.114，8.8.8.8，或者搜一下你当地网络运营商的dns"
        },
        {
            "mid": "81491",
            "mtime": "2023-12-30 06:10",
            "mcontent": "这种情况下，可能和MTU有关系。可以介绍一下网络的基本情况，路由器型号，上网是pppoe拨号，等等。"
        },
        {
            "mid": "65298830",
            "mtime": "2023-12-31 00:50",
            "mcontent": "电脑有没有开代理？开着的话关了试试；如果没有，查一下NGA的DNS解析，看和手机端是否一致，不一致刷新下DNS缓存看看"
        },
        {
            "mid": "1326743",
            "mtime": "2023-12-31 10:47",
            "mcontent": "最简单的就是360网络优化下，或者自己熟悉怎么修改dns，改成楼上说的"
        }
    ]
}