{
    "link": "https://bbs.nga.cn/read.php?tid=43314165",
    "title": "求教sql学习路径",
    "post_time": "2025-02-18 17:14",
    "uid": "65210484",
    "content": "文科生，寻思着空窗期学点使用技能，已经配置了sql环境只差系统学习了，请问各位大佬有没有推荐的教程，感激不尽",
    "replies": [
        {
            "mid": "63954270",
            "mtime": "2025-02-18 18:37",
            "mcontent": "B站有很多"
        },
        {
            "mid": "12194861",
            "mtime": "2025-02-18 21:06",
            "mcontent": "找一些练习数据，以实际需求学习和理解sql。这样比较快。"
        },
        {
            "mid": "64902933",
            "mtime": "2025-02-18 21:31",
            "mcontent": "英文水平在线的话，可以看一看 Mosh Hamedani 的 SQL 视频，B 站有转载。"
        },
        {
            "mid": "40602970",
            "mtime": "2025-02-19 00:28",
            "mcontent": "sql 必知必会，一天看完就能上手了"
        },
        {
            "mid": "41799311",
            "mtime": "2025-02-24 15:11",
            "mcontent": "[https:://sqlmother.yupi.icu/#/learn 此网页不属于本网站，不保证其安全性  继续访问       取消 https://sqlmother.yupi.icu/#/learn https://sqlmother.yupi.icu/#/learn] 照上面课程学习下"
        },
        {
            "mid": "65207630",
            "mtime": "2025-02-27 12:46",
            "mcontent": "学一下mysql必知必会，然后就可以问gpt帮写代码了"
        },
        {
            "mid": "64219520",
            "mtime": "2025-03-02 15:55",
            "mcontent": "程序员的编程电子书库(计算机专业学生必备)[https:://www.alipan.com/s/X5iBn9Vwx7a 此网页不属于本网站，不保证其安全性  继续访问       取消 https://www.alipan.com/s/X5iBn9Vwx7a https://www.alipan.com/s/X5iBn9Vwx7a]点击链接保存，或者复制本段内容，打开'阿里云盘'APP ，无需下载极速在线查看，视频原画倍速播放。"
        },
        {
            "mid": "43331470",
            "mtime": "2025-03-04 15:06",
            "mcontent": "微信读书找书看"
        },
        {
            "mid": "15883150",
            "mtime": "2025-03-05 09:24",
            "mcontent": "1.理论固然重要，买一本 SQL入门书，但是实践更加重要。本机装个数据库mysql轻量的就行，语法差别不大，练起来。2.兴趣驱动是最好的老师。我大学学的就是计算机，学过数据库，但是我SQL写的不咋地，但是就业第一年恰逢某酒店企业数据库泄露，我下了2200W的数据导入到access里。。。地区，年龄，性别，时间，各种组合查询，可以让你真实体会什么叫做 兴趣 需求驱动数据治理"
        }
    ]
}