{
    "link": "https://bbs.nga.cn/read.php?tid=39856831",
    "title": "显示器红蓝白光闪",
    "post_time": "2024-04-13 16:32",
    "uid": "65697341",
    "content": "显示器开机进系统就 红蓝绿白光闪  进bios 或者安全模式都可以 但是正常开机就不行怎么回事 ，是显示器驱动板出问题了吗",
    "replies": [
        {
            "mid": "63772608",
            "mtime": "2024-04-14 13:18",
            "mcontent": "显卡禁用了，用核显看看是不是显卡驱动的问题"
        },
        {
            "mid": "65697341",
            "mtime": "2024-04-14 18:32",
            "mcontent": "u没有带集显，安全模式下能操作吗？五一回家试试再不行就换显示器了"
        }
    ]
}