{
    "link": "https://bbs.nga.cn/read.php?tid=39631223",
    "title": "求助 遇到一个上网疑难杂症",
    "post_time": "2024-03-21 19:52",
    "uid": "65463875",
    "content": "情况是这样的：",
    "replies": [
        {
            "mid": "64057759",
            "mtime": "2024-03-21 23:05",
            "mcontent": "想不到什么原因，我的推荐 重装chrome"
        },
        {
            "mid": "62945847",
            "mtime": "2024-03-22 00:02",
            "mcontent": "查下打游戏是不是用了某些加速器flush dns"
        },
        {
            "mid": "485898",
            "mtime": "2024-03-25 15:10",
            "mcontent": "你多半是在没关梯子的情况下直接关机了，在网络和internet里面代理关掉就好了。。"
        }
    ]
}