{
    "link": "https://bbs.nga.cn/read.php?tid=43747491",
    "title": "[求助] 一线设备厂商社畜",
    "post_time": "2025-04-06 23:53",
    "uid": "62751251",
    "content": "最近闲来无事感觉工资有点低的无法满足自己需求，想接点外快，远程调试处理设备厂商的产品，主要是网安设备，安防设备这些，有没有老哥之前搞过这种或者这方面的，求指路",
    "replies": [
        {
            "mid": "62751251",
            "mtime": "2025-04-06 23:58",
            "mcontent": "看了下淘宝上需要开店的话就还需要上传执照这些，如果去申请的话害怕被公司审查到，看了下都是一代这些在淘宝割韭菜的操作"
        },
        {
            "mid": "42989625",
            "mtime": "2025-04-11 15:36",
            "mcontent": "去闲鱼试试，咸鱼上好像不需要。"
        }
    ]
}