{
    "link": "https://bbs.nga.cn/read.php?tid=40698606",
    "title": "[求助] 青龙面板拉不下来是怎么回事？",
    "post_time": "2024-06-28 16:03",
    "uid": "18548195",
    "content": "按照网上教程配置好了环境，但是不管是wsl还是宝塔面板或者直接docker，到最后这一步都不行",
    "replies": [
        {
            "mid": "63807600",
            "mtime": "2024-06-28 17:28",
            "mcontent": "[https://www.bilibili.com/video/BV1Em421L7xQ https://www.bilibili.com/video/BV1Em421L7xQ]▸[https:://github.com/DaoCloud/public-image-mirror 此网页不属于本网站，不保证其安全性  继续访问       取消 https://github.com/DaoCloud/public-image-mirror https://github.com/DaoCloud/public-image-mirror]"
        }
    ]
}