{
    "link": "https://bbs.nga.cn/read.php?tid=41708476",
    "title": "产品经理岗求内推",
    "post_time": "2024-09-18 17:57",
    "uid": "64911530",
    "content": "base：广州",
    "replies": [
        {
            "mid": "63422709",
            "mtime": "2024-09-19 13:55",
            "mcontent": "转产品好转吗"
        },
        {
            "mid": "65638731",
            "mtime": "2024-09-20 20:37",
            "mcontent": "做的什么产品，斯凯奇内部在招产品我可以帮你推推看"
        },
        {
            "mid": "64911530",
            "mtime": "2024-09-23 14:52",
            "mcontent": "不好转"
        },
        {
            "mid": "64911530",
            "mtime": "2024-09-23 15:01",
            "mcontent": "中后台系统或者小程序app这样的互联网产品  能内推吗  有报酬"
        },
        {
            "mid": "65638731",
            "mtime": "2024-09-23 20:58",
            "mcontent": "甩个联系方式"
        },
        {
            "mid": "64911530",
            "mtime": "2024-10-11 15:57",
            "mcontent": "私信你了哈，谢谢"
        }
    ]
}