{
    "link": "https://bbs.nga.cn/read.php?tid=41982007",
    "title": "u盘读不出来怎么办啊",
    "post_time": "2024-10-09 10:51",
    "uid": "64796647",
    "content": "如图E盘显示了一会儿，加载了一会儿干脆e盘就不显示了。怎么解决啊，各位大佬",
    "replies": [
        {
            "mid": "65993711",
            "mtime": "2024-10-09 11:22",
            "mcontent": "如果电脑接口没问题那大概是USB寄了"
        },
        {
            "mid": "64796647",
            "mtime": "2024-10-09 11:24",
            "mcontent": "硬件坏了好像是"
        },
        {
            "mid": "61745018",
            "mtime": "2024-10-11 15:25",
            "mcontent": "一般先看设备管理器读出来没，如果显示未知设备啥的可能还有救。要是设备管理器都没的话就排查一下接口问题，如果接口没事那就是U盘寄了"
        }
    ]
}