{
    "link": "https://bbs.nga.cn/read.php?tid=43534600",
    "title": "cuda和rocm平台对比",
    "post_time": "2025-03-14 17:11",
    "uid": "60273207",
    "content": "大佬们，就目前情况来看Linux +rocm和windows+cuda，哪个平台更好一点",
    "replies": [
        {
            "mid": "41719364",
            "mtime": "2025-03-14 18:12",
            "mcontent": "linux + cuda"
        },
        {
            "mid": "544943",
            "mtime": "2025-03-14 19:07",
            "mcontent": "不是哥们，完美避开正确选项"
        },
        {
            "mid": "61875796",
            "mtime": "2025-03-14 20:10",
            "mcontent": "win启动就吃1g多显存，跑32bq4长上下文就容易爆"
        },
        {
            "mid": "60273207",
            "mtime": "2025-03-16 19:27",
            "mcontent": "这不是太贫穷了吗"
        },
        {
            "mid": "64339374",
            "mtime": "2025-03-20 16:48",
            "mcontent": "看跑多大的模型了啊，理论上肯定 cuda 好，实际上嘛。。。可以看看b站的各路up主的测试就懂了。"
        }
    ]
}