{
    "link": "https://bbs.nga.cn/read.php?tid=40809167",
    "title": "没有统本，程序员这个圈子还能混吗",
    "post_time": "2024-07-08 19:20",
    "uid": "64547097",
    "content": "目前在上海34岁了，七八年前从php开始干起，后来转java再到golang，cicd等运维的活也一起干了，也带过4-5人团队。这样经验工作应该能找到的吧。。",
    "replies": [
        {
            "mid": "62349350",
            "mtime": "2024-07-08 22:08",
            "mcontent": "这种可能是单纯看你年龄大不好意思直接说所以卡你学历"
        },
        {
            "mid": "62661575",
            "mtime": "2024-07-08 23:21",
            "mcontent": "是的，转行吧"
        },
        {
            "mid": "62346010",
            "mtime": "2024-07-08 23:53",
            "mcontent": "干的这么杂，还啥经验呀，技术指定一般，这个年龄技术不到位直接一棍子打死了"
        },
        {
            "mid": "64593201",
            "mtime": "2024-07-09 14:09",
            "mcontent": "我比你还大一岁，现在小外企苟着。 感觉现在要找工作的话海投太难了，中年人再去刷题背八股这些真的顶不住了看有没有朋友内推机会什么的"
        },
        {
            "mid": "33334349",
            "mtime": "2024-07-09 16:32",
            "mcontent": "我们这儿外包是不限制学历的，能拿个年包15-20万的样子正职不仅要统招本科，非名校的都得有人挺你走特批"
        },
        {
            "mid": "65756098",
            "mtime": "2024-07-12 17:44",
            "mcontent": "外包也不是不可以"
        }
    ]
}