{
    "link": "https://bbs.nga.cn/read.php?tid=38913410",
    "title": "求助 网页被黑了 客户打开跳转到别人的网页上",
    "post_time": "2024-01-06 07:54",
    "uid": "64305455",
    "content": "昨晚研究了一通，丝毫无对策，甚至我连它在什么情况下会跳都没研究出来，不知道他是什么概率跳什么条件跳，就是有两个顾客向我反馈了我才知道有这么个情况",
    "replies": [
        {
            "mid": "64305455",
            "mtime": "2024-01-06 08:20",
            "mcontent": ""
        },
        {
            "mid": "43083619",
            "mtime": "2024-01-06 09:05",
            "mcontent": "难道不是去你的服务器上面看一看么？"
        },
        {
            "mid": "41786417",
            "mtime": "2024-01-06 10:31",
            "mcontent": "有没有可能是客户被dns劫持了"
        },
        {
            "mid": "26606137",
            "mtime": "2024-01-06 11:01",
            "mcontent": "两个客户跳的是同一个网站吗  不是同一个 大概率是有垃圾软件劫持了浏览器"
        },
        {
            "mid": "731907",
            "mtime": "2024-01-06 11:05",
            "mcontent": "下载服务器的网站文件，和你本机备份的网站文件，用文件对比软件比如Beyond Compare对比差异不过你不把漏洞补上，仍然还是会被黑。"
        }
    ]
}