{
    "link": "https://bbs.nga.cn/read.php?tid=39176501",
    "title": "[求助]求大伙给应届一年被裁指条出路",
    "post_time": "2024-02-01 20:47",
    "uid": "64206184",
    "content": "某985本科计算机专业，22年毕业生。当时正值互联网寒冬的前夕，秋招拿了个大厂的offer，总包40多w了。当时觉得虽然在里面打杂，但如果能一直混下去小日子也能过的不错。",
    "replies": [
        {
            "mid": "41224420",
            "mtime": "2024-02-02 08:24",
            "mcontent": "建议考研洗履历吧，到时候本硕985出来又是一条好汉。你现在就算力扣刷穿，人事这关也不一定好过，除非你接受消费降级去中小作坊，但我觉得你也不太能接受。春招学一点框架，再试试社招，一些国企还比较喜欢985来撑场子。要是四月中搞不定赶紧准备考研吧。985本科应试这块肯定没问题，11408或者自命题该考的考。"
        },
        {
            "mid": "64206184",
            "mtime": "2024-02-01 21:15",
            "mcontent": "好，谢谢老哥，我再试两个月"
        },
        {
            "mid": "63782286",
            "mtime": "2024-02-01 21:40",
            "mcontent": "听着挺吓人的，没有找人内推吗？现在一般的公司应该是锁hc，最多给点外包的hc。可能是要等经济回暖。"
        },
        {
            "mid": "60474355",
            "mtime": "2024-02-01 22:20",
            "mcontent": "是不是简历写的有问题呢？ 找人看看简历。985科班一年大厂经验不至于捞不到面试机会吧华为od 985 基本点击就送，但是很多组的od的实际也是干杂活累活的，运维交付啥的，od转华为基本没啥希望。"
        },
        {
            "mid": "42252406",
            "mtime": "2024-02-01 22:48",
            "mcontent": "一开始能拿40w包的水平。这年头建议先砍到20w去其它大厂看看。。。。"
        },
        {
            "mid": "38056782",
            "mtime": "2024-02-02 00:51",
            "mcontent": "你如果打算考研能保证一次考上吗？22年的毕业生我估计应该在24岁左右吧，到时候读研出来都28甚至29了，年龄是个大问题"
        },
        {
            "mid": "62570266",
            "mtime": "2024-02-02 02:35",
            "mcontent": "原来这就是版本t0吗，本科出来总包40个回来吧t0计算机我最骄傲的专业本科毕业40w眼泪莫名在流淌"
        },
        {
            "mid": "61682826",
            "mtime": "2024-02-02 08:24",
            "mcontent": "去香港读研呗考什么研 纯粹浪费时间985 申个还不是点击就送"
        },
        {
            "mid": "60189649",
            "mtime": "2024-02-02 08:47",
            "mcontent": "要是能去华为OD收入也不低啊"
        },
        {
            "mid": "63366654",
            "mtime": "2024-02-02 10:29",
            "mcontent": "因为22年秋招是近几年最简单的一年，当年互联网大厂普遍误判未来形势，疯狂扩张，秋招人数比22年之前翻了约一倍，为了抢人工资也开到了历年最高，往后23年发现就是大裁员+几乎不招人+降校招base"
        },
        {
            "mid": "62840502",
            "mtime": "2024-02-02 13:56",
            "mcontent": "只会力扣已经寄了一半了非大厂进面试一般只看选择题，程序题有写就行反正不会去看的，因为hr不会花几个月补上框架"
        },
        {
            "mid": "42696145",
            "mtime": "2024-02-02 16:04",
            "mcontent": "java但是不会spring=不会java=没人公司敢要"
        },
        {
            "mid": "2504017",
            "mtime": "2024-02-02 21:29",
            "mcontent": "不会spring在厂商眼里等价于不会java"
        },
        {
            "mid": "42641942",
            "mtime": "2024-02-02 22:08",
            "mcontent": "真假的？985计算机+大厂40w，出来不好找工作？"
        },
        {
            "mid": "65377956",
            "mtime": "2024-02-03 06:44",
            "mcontent": "去拼多多吧，拼多多累是累了点，但面试难度点击即送"
        },
        {
            "mid": "4691144",
            "mtime": "2024-02-23 01:36",
            "mcontent": "别听楼上让你去考研和什么降到20w的扯淡就算你顺利考上了，一切顺利，3年后行情也没有变得更差，你校招又进了大厂，然后呢？26岁的P5还是P4？现在这些大厂年龄卡的有多严你也应该知道还有20w的，哪个大厂有20w的岗位？还是要自信一点，简历和项目好好整一整，985+一年大厂经验不至于找不到工作，你要想连你这个背景都找不到，那还有几个人能找到？"
        },
        {
            "mid": "6112087",
            "mtime": "2024-03-05 22:47",
            "mcontent": "20年下半年到21年底左右那段时间确实狠。疫情控制好的原因，整个互联网行业都对未来盲目乐观。我20年底从头部外企跳回国内互联网，大厂offer拿到手软，基本都是总包double起步。然后22年开始瞬间就不好了"
        },
        {
            "mid": "64948728",
            "mtime": "2024-03-06 05:19",
            "mcontent": "24年咋样？"
        }
    ]
}